[
  {
    "id": "dragapult-ex",
    "name": "Dragapult ex",
    "icons": "[\"dragapult\"]",
    "total_entries": 1506,
    "top_cut_entries": 0,
    "representation_pct": 0.4568,
    "conversion_rate": 0,
    "wins": 0,
    "losses": 0,
    "ties": 0,
    "last_updated": "2026-05-16",
    "velocity": 0,
    "image_url": "https://r2.limitlesstcg.net/pokemon/gen9/dragapult.png",
    "rank": 1,
    "points": 1506,
    "share": 45.68,
    "limitless_id": 284
  },
  {
    "id": "crustle-mysterious-rock-inn",
    "name": "Crustle Mysterious Rock Inn",
    "icons": "[\"crustle\"]",
    "total_entries": 200,
    "top_cut_entries": 0,
    "representation_pct": 0.0607,
    "conversion_rate": 0,
    "wins": 0,
    "losses": 0,
    "ties": 0,
    "last_updated": "2026-05-16",
    "velocity": 0,
    "image_url": "https://r2.limitlesstcg.net/pokemon/gen9/crustle.png",
    "rank": 2,
    "points": 200,
    "share": 6.07,
    "limitless_id": 341
  },
  {
    "id": "raging-bolt-ex",
    "name": "Raging Bolt ex",
    "icons": "[\"raging-bolt\"]",
    "total_entries": 196,
    "top_cut_entries": 0,
    "representation_pct": 0.0594,
    "conversion_rate": 0,
    "wins": 0,
    "losses": 0,
    "ties": 0,
    "last_updated": "2026-05-16",
    "velocity": 0,
    "image_url": "https://r2.limitlesstcg.net/pokemon/gen9/raging-bolt.png",
    "rank": 3,
    "points": 196,
    "share": 5.94,
    "limitless_id": 280
  },
  {
    "id": "rocket-s-mewtwo-ex",
    "name": "Rocket's Mewtwo ex",
    "icons": "[\"mewtwo\", \"spidops\"]",
    "total_entries": 196,
    "top_cut_entries": 0,
    "representation_pct": 0.0594,
    "conversion_rate": 0,
    "wins": 0,
    "losses": 0,
    "ties": 0,
    "last_updated": "2026-05-16",
    "velocity": 0,
    "image_url": "https://r2.limitlesstcg.net/pokemon/gen9/mewtwo.png",
    "rank": 3,
    "points": 196,
    "share": 5.94,
    "limitless_id": 337
  },
  {
    "id": "festival-lead",
    "name": "Festival Lead",
    "icons": "[\"dipplin\", \"thwackey\"]",
    "total_entries": 175,
    "top_cut_entries": 0,
    "representation_pct": 0.0531,
    "conversion_rate": 0,
    "wins": 0,
    "losses": 0,
    "ties": 0,
    "last_updated": "2026-05-16",
    "velocity": 0,
    "image_url": "https://r2.limitlesstcg.net/pokemon/gen9/dipplin.png",
    "rank": 5,
    "points": 175,
    "share": 5.31,
    "limitless_id": 336
  },
  {
    "id": "ogerpon-meganium",
    "name": "Ogerpon Meganium",
    "icons": "[\"ogerpon\", \"meganium\"]",
    "total_entries": 157,
    "top_cut_entries": 0,
    "representation_pct": 0.0476,
    "conversion_rate": 0,
    "wins": 0,
    "losses": 0,
    "ties": 0,
    "last_updated": "2026-05-16",
    "velocity": 0,
    "image_url": "https://r2.limitlesstcg.net/pokemon/gen9/ogerpon.png",
    "rank": 6,
    "points": 157,
    "share": 4.76,
    "limitless_id": 351
  },
  {
    "id": "cynthia-s-garchomp-ex",
    "name": "Cynthia's Garchomp ex",
    "icons": "[\"garchomp\"]",
    "total_entries": 139,
    "top_cut_entries": 0,
    "representation_pct": 0.0422,
    "conversion_rate": 0,
    "wins": 0,
    "losses": 0,
    "ties": 0,
    "last_updated": "2026-05-16",
    "velocity": 0,
    "image_url": "https://r2.limitlesstcg.net/pokemon/gen9/garchomp.png",
    "rank": 7,
    "points": 139,
    "share": 4.22,
    "limitless_id": 332
  },
  {
    "id": "alakazam-powerful-hand",
    "name": "Alakazam Powerful Hand",
    "icons": "[\"alakazam\"]",
    "total_entries": 106,
    "top_cut_entries": 0,
    "representation_pct": 0.0322,
    "conversion_rate": 0,
    "wins": 0,
    "losses": 0,
    "ties": 0,
    "last_updated": "2026-05-16",
    "velocity": 0,
    "image_url": "https://r2.limitlesstcg.net/pokemon/gen9/alakazam.png",
    "rank": 8,
    "points": 106,
    "share": 3.22,
    "limitless_id": 350
  },
  {
    "id": "n-s-zoroark-ex",
    "name": "N's Zoroark ex",
    "icons": "[\"zoroark\"]",
    "total_entries": 83,
    "top_cut_entries": 0,
    "representation_pct": 0.0252,
    "conversion_rate": 0,
    "wins": 0,
    "losses": 0,
    "ties": 0,
    "last_updated": "2026-05-16",
    "velocity": 0,
    "image_url": "https://r2.limitlesstcg.net/pokemon/gen9/zoroark.png",
    "rank": 9,
    "points": 83,
    "share": 2.52,
    "limitless_id": 320
  },
  {
    "id": "mega-lucario-ex",
    "name": "Mega Lucario ex",
    "icons": "[\"lucario-mega\"]",
    "total_entries": 73,
    "top_cut_entries": 0,
    "representation_pct": 0.0221,
    "conversion_rate": 0,
    "wins": 0,
    "losses": 0,
    "ties": 0,
    "last_updated": "2026-05-16",
    "velocity": 0,
    "image_url": "https://r2.limitlesstcg.net/pokemon/gen9/lucario-mega.png",
    "rank": 10,
    "points": 73,
    "share": 2.21,
    "limitless_id": 345
  },
  {
    "id": "mega-starmie-ex",
    "name": "Mega Starmie ex",
    "icons": "[\"starmie-mega\"]",
    "total_entries": 73,
    "top_cut_entries": 0,
    "representation_pct": 0.0221,
    "conversion_rate": 0,
    "wins": 0,
    "losses": 0,
    "ties": 0,
    "last_updated": "2026-05-16",
    "velocity": 0,
    "image_url": "https://r2.limitlesstcg.net/pokemon/gen9/starmie-mega.png",
    "rank": 10,
    "points": 73,
    "share": 2.21,
    "limitless_id": 362
  },
  {
    "id": "ogerpon-box",
    "name": "Ogerpon Box",
    "icons": "[\"ogerpon\", \"ogerpon-wellspring\"]",
    "total_entries": 69,
    "top_cut_entries": 0,
    "representation_pct": 0.0209,
    "conversion_rate": 0,
    "wins": 0,
    "losses": 0,
    "ties": 0,
    "last_updated": "2026-05-16",
    "velocity": 0,
    "image_url": "https://r2.limitlesstcg.net/pokemon/gen9/ogerpon.png",
    "rank": 12,
    "points": 69,
    "share": 2.09,
    "limitless_id": 339
  },
  {
    "id": "mega-lopunny-ex",
    "name": "Mega Lopunny ex",
    "icons": "[\"lopunny-mega\"]",
    "total_entries": 60,
    "top_cut_entries": 0,
    "representation_pct": 0.0182,
    "conversion_rate": 0,
    "wins": 0,
    "losses": 0,
    "ties": 0,
    "last_updated": "2026-05-16",
    "velocity": 0,
    "image_url": "https://r2.limitlesstcg.net/pokemon/gen9/lopunny-mega.png",
    "rank": 13,
    "points": 60,
    "share": 1.82,
    "limitless_id": 353
  },
  {
    "id": "okidogi-adrena-power",
    "name": "Okidogi Adrena-Power",
    "icons": "[\"okidogi\"]",
    "total_entries": 44,
    "top_cut_entries": 0,
    "representation_pct": 0.0133,
    "conversion_rate": 0,
    "wins": 0,
    "losses": 0,
    "ties": 0,
    "last_updated": "2026-05-16",
    "velocity": 0,
    "image_url": "https://r2.limitlesstcg.net/pokemon/gen9/okidogi.png",
    "rank": 14,
    "points": 44,
    "share": 1.33,
    "limitless_id": 293
  },
  {
    "id": "marnie-s-grimmsnarl-ex",
    "name": "Marnie's Grimmsnarl ex",
    "icons": "[\"grimmsnarl\"]",
    "total_entries": 33,
    "top_cut_entries": 0,
    "representation_pct": 0.01,
    "conversion_rate": 0,
    "wins": 0,
    "losses": 0,
    "ties": 0,
    "last_updated": "2026-05-16",
    "velocity": 0,
    "image_url": "https://r2.limitlesstcg.net/pokemon/gen9/grimmsnarl.png",
    "rank": 15,
    "points": 33,
    "share": 1.0,
    "limitless_id": 329
  },
  {
    "id": "tera-box",
    "name": "Tera Box",
    "icons": "[\"noctowl\", \"ogerpon-wellspring\"]",
    "total_entries": 30,
    "top_cut_entries": 0,
    "representation_pct": 0.0091,
    "conversion_rate": 0,
    "wins": 0,
    "losses": 0,
    "ties": 0,
    "last_updated": "2026-05-16",
    "velocity": 0,
    "image_url": "https://r2.limitlesstcg.net/pokemon/gen9/noctowl.png",
    "rank": 16,
    "points": 30,
    "share": 0.91,
    "limitless_id": 321
  },
  {
    "id": "lillie-s-clefairy-ex",
    "name": "Lillie's Clefairy ex",
    "icons": "[\"clefairy\"]",
    "total_entries": 30,
    "top_cut_entries": 0,
    "representation_pct": 0.0091,
    "conversion_rate": 0,
    "wins": 0,
    "losses": 0,
    "ties": 0,
    "last_updated": "2026-05-16",
    "velocity": 0,
    "image_url": "https://r2.limitlesstcg.net/pokemon/gen9/clefairy.png",
    "rank": 16,
    "points": 30,
    "share": 0.91,
    "limitless_id": 326
  },
  {
    "id": "rocket-s-honchkrow",
    "name": "Rocket's Honchkrow",
    "icons": "[\"honchkrow\", \"porygon2\"]",
    "total_entries": 25,
    "top_cut_entries": 0,
    "representation_pct": 0.0076,
    "conversion_rate": 0,
    "wins": 0,
    "losses": 0,
    "ties": 0,
    "last_updated": "2026-05-16",
    "velocity": 0,
    "image_url": "https://r2.limitlesstcg.net/pokemon/gen9/honchkrow.png",
    "rank": 18,
    "points": 25,
    "share": 0.76,
    "limitless_id": 356
  },
  {
    "id": "slowking-seek-inspiration",
    "name": "Slowking Seek Inspiration",
    "icons": "[\"slowking\"]",
    "total_entries": 23,
    "top_cut_entries": 0,
    "representation_pct": 0.007,
    "conversion_rate": 0,
    "wins": 0,
    "losses": 0,
    "ties": 0,
    "last_updated": "2026-05-16",
    "velocity": 0,
    "image_url": "https://r2.limitlesstcg.net/pokemon/gen9/slowking.png",
    "rank": 19,
    "points": 23,
    "share": 0.7,
    "limitless_id": 322
  },
  {
    "id": "hydrapple-ex",
    "name": "Hydrapple ex",
    "icons": "[\"hydrapple\"]",
    "total_entries": 20,
    "top_cut_entries": 0,
    "representation_pct": 0.0061,
    "conversion_rate": 0,
    "wins": 0,
    "losses": 0,
    "ties": 0,
    "last_updated": "2026-05-16",
    "velocity": 0,
    "image_url": "https://r2.limitlesstcg.net/pokemon/gen9/hydrapple.png",
    "rank": 20,
    "points": 20,
    "share": 0.61,
    "limitless_id": 352
  },
  {
    "id": "mega-absol-box",
    "name": "Mega Absol Box",
    "icons": "[\"absol-mega\", \"kangaskhan-mega\"]",
    "total_entries": 14,
    "top_cut_entries": 0,
    "representation_pct": 0.0042,
    "conversion_rate": 0,
    "wins": 0,
    "losses": 0,
    "ties": 0,
    "last_updated": "2026-05-16",
    "velocity": 0,
    "image_url": "https://r2.limitlesstcg.net/pokemon/gen9/absol-mega.png",
    "rank": 21,
    "points": 14,
    "share": 0.42,
    "limitless_id": 344
  },
  {
    "id": "hop-s-trevenant",
    "name": "Hop's Trevenant",
    "icons": "[\"trevenant\"]",
    "total_entries": 13,
    "top_cut_entries": 0,
    "representation_pct": 0.0039,
    "conversion_rate": 0,
    "wins": 0,
    "losses": 0,
    "ties": 0,
    "last_updated": "2026-05-16",
    "velocity": 0,
    "image_url": "https://r2.limitlesstcg.net/pokemon/gen9/trevenant.png",
    "rank": 22,
    "points": 13,
    "share": 0.39,
    "limitless_id": 363
  },
  {
    "id": "greninja-ex",
    "name": "Greninja ex",
    "icons": "[\"greninja\"]",
    "total_entries": 9,
    "top_cut_entries": 0,
    "representation_pct": 0.0027,
    "conversion_rate": 0,
    "wins": 0,
    "losses": 0,
    "ties": 0,
    "last_updated": "2026-05-16",
    "velocity": 0,
    "image_url": "https://r2.limitlesstcg.net/pokemon/gen9/greninja.png",
    "rank": 23,
    "points": 9,
    "share": 0.27,
    "limitless_id": 287
  },
  {
    "id": "archaludon-ex",
    "name": "Archaludon ex",
    "icons": "[\"archaludon\"]",
    "total_entries": 5,
    "top_cut_entries": 0,
    "representation_pct": 0.0015,
    "conversion_rate": 0,
    "wins": 0,
    "losses": 0,
    "ties": 0,
    "last_updated": "2026-05-16",
    "velocity": 0,
    "image_url": "https://r2.limitlesstcg.net/pokemon/gen9/archaludon.png",
    "rank": 24,
    "points": 5,
    "share": 0.15,
    "limitless_id": 315
  },
  {
    "id": "ethan-s-typhlosion",
    "name": "Ethan's Typhlosion",
    "icons": "[\"typhlosion\"]",
    "total_entries": 5,
    "top_cut_entries": 0,
    "representation_pct": 0.0015,
    "conversion_rate": 0,
    "wins": 0,
    "losses": 0,
    "ties": 0,
    "last_updated": "2026-05-16",
    "velocity": 0,
    "image_url": "https://r2.limitlesstcg.net/pokemon/gen9/typhlosion.png",
    "rank": 24,
    "points": 5,
    "share": 0.15,
    "limitless_id": 333
  },
  {
    "id": "flareon-ex",
    "name": "Flareon ex",
    "icons": "[\"flareon\"]",
    "total_entries": 4,
    "top_cut_entries": 0,
    "representation_pct": 0.0012,
    "conversion_rate": 0,
    "wins": 0,
    "losses": 0,
    "ties": 0,
    "last_updated": "2026-05-16",
    "velocity": 0,
    "image_url": "https://r2.limitlesstcg.net/pokemon/gen9/flareon.png",
    "rank": 26,
    "points": 4,
    "share": 0.12,
    "limitless_id": 319
  },
  {
    "id": "bloodmoon-ursaluna-mad-bite",
    "name": "Bloodmoon Ursaluna Mad Bite",
    "icons": "[\"ursaluna-bloodmoon\"]",
    "total_entries": 3,
    "top_cut_entries": 0,
    "representation_pct": 0.0009,
    "conversion_rate": 0,
    "wins": 0,
    "losses": 0,
    "ties": 0,
    "last_updated": "2026-05-16",
    "velocity": 0,
    "image_url": "https://r2.limitlesstcg.net/pokemon/gen9/ursaluna-bloodmoon.png",
    "rank": 27,
    "points": 3,
    "share": 0.09,
    "limitless_id": 291
  },
  {
    "id": "mega-venusaur-ex",
    "name": "Mega Venusaur ex",
    "icons": "[\"venusaur-mega\"]",
    "total_entries": 3,
    "top_cut_entries": 0,
    "representation_pct": 0.0009,
    "conversion_rate": 0,
    "wins": 0,
    "losses": 0,
    "ties": 0,
    "last_updated": "2026-05-16",
    "velocity": 0,
    "image_url": "https://r2.limitlesstcg.net/pokemon/gen9/venusaur-mega.png",
    "rank": 27,
    "points": 3,
    "share": 0.09,
    "limitless_id": 346
  },
  {
    "id": "mega-froslass-ex",
    "name": "Mega Froslass ex",
    "icons": "[\"froslass-mega\"]",
    "total_entries": 3,
    "top_cut_entries": 0,
    "representation_pct": 0.0009,
    "conversion_rate": 0,
    "wins": 0,
    "losses": 0,
    "ties": 0,
    "last_updated": "2026-05-16",
    "velocity": 0,
    "image_url": "https://r2.limitlesstcg.net/pokemon/gen9/froslass-mega.png",
    "rank": 27,
    "points": 3,
    "share": 0.09,
    "limitless_id": 360
  }
]